[
  { "name": "Vistalba", "id": 3832509 },
  { "name": "Vista Flores", "id": 3832512 },
  { "name": "Villa Nueva", "id": 3832661 },
  { "name": "Villa Atuel", "id": 3832803 },
  { "name": "Uspallata", "id": 3833358 },
  { "name": "San Rafael", "id": 3836669 },
  { "name": "Rodeo del Medio", "id": 3838684 },
  { "name": "Rivadavia", "id": 3838759 },
  { "name": "Real del Padre", "id": 3839288 },
  { "name": "Medrano", "id": 3844473 },
  { "name": "Luzuriaga", "id": 3845350 },
  { "name": "Las Heras", "id": 3848353 },
  { "name": "Las Heras", "id": 3848354 },
  { "name": "Las Catitas", "id": 3848611 },
  { "name": "La Puntilla", "id": 3849181 },
  { "name": "La Paz", "id": 3849516 },
  { "name": "La Consulta", "id": 3851913 },
  { "name": "Goudge", "id": 3854916 },
  { "name": "Gobernador Benegas", "id": 3854993 },
  { "name": "Eugenio Bustos", "id": 3855715 },
  { "name": "El Plumerillo", "id": 3857216 },
  { "name": "Costa de Araujo", "id": 3859956 },
  { "name": "Coquimbito", "id": 3860280 },
  { "name": "Chapanay", "id": 3861713 },
  { "name": "Chacras de Coria", "id": 3861869 },
  { "name": "Bowen", "id": 3863887 },
  { "name": "Bermejo", "id": 3864299 },
  { "name": "Agrelo", "id": 3866905 }
]
